coqui_stt_server/__init__.py
coqui_stt_server/__main__.py
coqui_stt_server/modelmanager.py
coqui_stt_server/server.py
coqui_stt_server/static/bootstrap-icons.css
coqui_stt_server/static/bootstrap.min.css
coqui_stt_server/static/coqui-STT-logo-green.png
coqui_stt_server/static/style.css
coqui_stt_server/static/build/asset-manifest.json
coqui_stt_server/static/build/downsampling_worker.js
coqui_stt_server/static/build/favicon.ico
coqui_stt_server/static/build/index.html
coqui_stt_server/static/build/logo192.png
coqui_stt_server/static/build/logo512.png
coqui_stt_server/static/build/manifest.json
coqui_stt_server/static/build/precache-manifest.9cc7c6a92923dd552119081f7d651d57.js
coqui_stt_server/static/build/robots.txt
coqui_stt_server/static/build/service-worker.js
coqui_stt_server/static/build/static/css/bundle.min.css
coqui_stt_server/static/build/static/css/bundle.min.css.map
coqui_stt_server/static/build/static/js/bundle.min.js
coqui_stt_server/static/build/static/js/bundle.min.js.LICENSE.txt
coqui_stt_server/static/build/static/js/bundle.min.js.map
coqui_stt_server/static/fonts/bootstrap-icons.woff
coqui_stt_server/static/fonts/bootstrap-icons.woff2
coqui_stt_server/templates/base.html
coqui_stt_server/templates/index.html
coqui_stt_server/templates/transcribe.html
coqui_stt_server-0.0.8.dist-info/LICENSE
coqui_stt_server-0.0.8.dist-info/METADATA
coqui_stt_server-0.0.8.dist-info/WHEEL
coqui_stt_server-0.0.8.dist-info/entry_points.txt
coqui_stt_server-0.0.8.dist-info/top_level.txt
coqui_stt_server-0.0.8.dist-info/RECORD
