Metadata-Version: 2.1
Name: coqui-stt-server
Version: 0.0.8
Summary: A local server for Coqui STT models
Home-page: https://github.com/coqui-ai/stt-server
Author: Coqui GmbH
Author-email: info@coqui.ai
License: MPL-2.0
Platform: UNKNOWN
Classifier: Development Status :: 3 - Alpha
Classifier: Intended Audience :: Developers
Classifier: Topic :: Multimedia :: Sound/Audio :: Speech
Classifier: License :: OSI Approved :: Mozilla Public License 2.0 (MPL 2.0)
Classifier: Programming Language :: Python :: 3
Requires-Python: <4,>=3.6
License-File: LICENSE
Requires-Dist: Jinja2 (==3.0.1)
Requires-Dist: Flask (==2.0.1)
Requires-Dist: Flask-Cors (==3.0.10)
Requires-Dist: pyxdg (==0.27)
Requires-Dist: coqpit (==0.0.9)
Requires-Dist: Flask-SocketIO (==4.3.2)
Requires-Dist: webrtcvad (==2.0.10)
Requires-Dist: stt (==0.10.0a6)
Requires-Dist: requests (==2.25.1)
